twindb_table_compare/__init__.py
twindb_table_compare/cli.py
twindb_table_compare/compare.py
twindb_table_compare-3.0.3.dist-info/AUTHORS.rst
twindb_table_compare-3.0.3.dist-info/LICENSE
twindb_table_compare-3.0.3.dist-info/METADATA
twindb_table_compare-3.0.3.dist-info/WHEEL
twindb_table_compare-3.0.3.dist-info/entry_points.txt
twindb_table_compare-3.0.3.dist-info/top_level.txt
twindb_table_compare-3.0.3.dist-info/RECORD
