Metadata-Version: 2.1
Name: twindb-table-compare
Version: 3.0.3
Summary: TwinDB Table Compare reads percona.checksums from the master and slave and shows what records are difference if there are any inconsistencies.
Home-page: https://github.com/twindb/twindb-table-compare
Author: Aleksandr Kuzminsky
Author-email: aleks@twindb.com
License: Apache Software License 2.0
Keywords: twindb_table_compare
Platform: UNKNOWN
Classifier: Development Status :: 5 - Production/Stable
Classifier: Environment :: Console
Classifier: Intended Audience :: Developers
Classifier: License :: OSI Approved :: Apache Software License
Classifier: Natural Language :: English
Classifier: Programming Language :: Python :: 3
Classifier: Programming Language :: Python :: 3.6
Classifier: Programming Language :: Python :: 3.7
Classifier: Programming Language :: Python :: 3.8
Classifier: Topic :: Database
Classifier: Topic :: Database :: Database Engines/Servers
Requires-Dist: click (~=7.0)
Requires-Dist: logutils (~=0.3)
Requires-Dist: pymysql (~=0.9)
